kumosearch/__init__.py
kumosearch/alias.py
kumosearch/aliases.py
kumosearch/analytics.py
kumosearch/analytics_rule.py
kumosearch/analytics_rules.py
kumosearch/api_call.py
kumosearch/client.py
kumosearch/collection.py
kumosearch/collections.py
kumosearch/configuration.py
kumosearch/conversation_model.py
kumosearch/conversations_models.py
kumosearch/debug.py
kumosearch/document.py
kumosearch/documents.py
kumosearch/exceptions.py
kumosearch/key.py
kumosearch/keys.py
kumosearch/logger.py
kumosearch/multi_search.py
kumosearch/operations.py
kumosearch/override.py
kumosearch/overrides.py
kumosearch/preprocess.py
kumosearch/stopwords.py
kumosearch/stopwords_set.py
kumosearch/synonym.py
kumosearch/synonyms.py
kumosearch/validation.py
kumosearch-1.1.0.dist-info/LICENSE
kumosearch-1.1.0.dist-info/METADATA
kumosearch-1.1.0.dist-info/WHEEL
kumosearch-1.1.0.dist-info/top_level.txt
kumosearch-1.1.0.dist-info/RECORD
